CHANGES.rst
CONTRIBUTORS.rst
DEVELOP.rst
LICENSE.rst
MANIFEST.in
README.rst
setup.cfg
setup.py
docs/index.rst
src/collective/__init__.py
src/collective.restapi.navigationtree.egg-info/PKG-INFO
src/collective.restapi.navigationtree.egg-info/SOURCES.txt
src/collective.restapi.navigationtree.egg-info/dependency_links.txt
src/collective.restapi.navigationtree.egg-info/entry_points.txt
src/collective.restapi.navigationtree.egg-info/namespace_packages.txt
src/collective.restapi.navigationtree.egg-info/not-zip-safe
src/collective.restapi.navigationtree.egg-info/requires.txt
src/collective.restapi.navigationtree.egg-info/top_level.txt
src/collective/restapi/__init__.py
src/collective/restapi/navigationtree/__init__.py
src/collective/restapi/navigationtree/configure.zcml
src/collective/restapi/navigationtree/interfaces.py
src/collective/restapi/navigationtree/permissions.zcml
src/collective/restapi/navigationtree/setuphandlers.py
src/collective/restapi/navigationtree/testing.py
src/collective/restapi/navigationtree/upgrades.py
src/collective/restapi/navigationtree/upgrades.zcml
src/collective/restapi/navigationtree/browser/__init__.py
src/collective/restapi/navigationtree/browser/configure.zcml
src/collective/restapi/navigationtree/browser/get.py
src/collective/restapi/navigationtree/locales/collective.restapi.navigationtree.pot
src/collective/restapi/navigationtree/locales/update.sh
src/collective/restapi/navigationtree/profiles/default/browserlayer.xml
src/collective/restapi/navigationtree/profiles/default/metadata.xml
src/collective/restapi/navigationtree/profiles/default/registry.xml
src/collective/restapi/navigationtree/profiles/default/rolemap.xml
src/collective/restapi/navigationtree/profiles/uninstall/browserlayer.xml
src/collective/restapi/navigationtree/tests/__init__.py
src/collective/restapi/navigationtree/tests/test_navigationtree.py
src/collective/restapi/navigationtree/tests/test_setup.py