Metadata-Version: 1.1
Name: collective.restapi.navigationtree
Version: 1.0a1
Summary: Provides a REST endpoint to query the site's navigation tree
Home-page: https://pypi.python.org/pypi/collective.restapi.navigationtree
Author: Fulvio Casali
Author-email: fulviocasali@gmail.com
License: GPL version 2
Keywords: Python Plone rest restful api json
Platform: UNKNOWN
Classifier: Environment :: Web Environment
Classifier: Framework :: Plone
Classifier: Framework :: Plone :: 4.3
Classifier: Framework :: Plone :: 5.0
Classifier: Framework :: Plone :: 5.1
Classifier: Intended Audience :: Developers
Classifier: Programming Language :: Python
Classifier: Programming Language :: Python :: 2.7
Classifier: Operating System :: OS Independent
Classifier: License :: OSI Approved :: GNU General Public License v2 (GPLv2)
Classifier: Topic :: Software Development :: Libraries :: Python Modules
